DesiredDateFormat/Convert.py
DesiredDateFormat/__init__.py
DesiredDateFormat-1.1.1.dist-info/LICENSE.txt
DesiredDateFormat-1.1.1.dist-info/METADATA
DesiredDateFormat-1.1.1.dist-info/WHEEL
DesiredDateFormat-1.1.1.dist-info/top_level.txt
DesiredDateFormat-1.1.1.dist-info/RECORD
