Metadata-Version: 2.1
Name: DesiredDateFormat
Version: 1.1.1
Summary: A library which converts any date into desired date format
Home-page: https://github.com/unnati-14/Python_-Library_DesiredDateFormat
Author: Unnati Singh
Author-email: singhunnati1401@gmail.com
License: UNKNOWN
Platform: UNKNOWN
Classifier: Programming Language :: Python :: 2
Classifier: Programming Language :: Python :: 3
Classifier: License :: OSI Approved :: MIT License
Classifier: Operating System :: OS Independent
Requires-Python: >=2
